{
  "type": "FeatureCollection",
  "features": [
    {
      "type": "Feature",
      "geometry": {
        "type": "LineString",
        "coordinates": [
          [
            1.90441,
            42.45896
          ],
          [
            1.86466,
            42.47416
          ],
          [
            1.86398,
            42.47443
          ],
          [
            1.82384,
            42.51491
          ],
          [
            1.82366,
            42.51509
          ],
          [
            1.82474,
            42.54041
          ],
          [
            1.8247,
            42.54053
          ],
          [
            1.79652,
            42.5859
          ],
          [
            1.79647,
            42.58608
          ],
          [
            1.82369,
            42.60518
          ],
          [
            1.82361,
            42.60475
          ],
          [
            1.81311,
            42.60742
          ],
          [
            1.81317,
            42.60769
          ],
          [
            1.83752,
            42.65985
          ],
          [
            1.83754,
            42.65998
          ],
          [
            1.82411,
            42.68563
          ],
          [
            1.82408,
            42.68596
          ],
          [
            1.8426,
            42.72239
          ],
          [
            1.84226,
            42.72283
          ],
          [
            1.65395,
            42.80009
          ],
          [
            1.65327,
            42.8004
          ],
          [
            1.60126,
            42.8456
          ],
          [
            1.60102,
            42.8462
          ],
          [
            1.64317,
            42.91088
          ],
          [
            1.64333,
            42.91202
          ],
          [
            1.60701,
            42.96907
          ],
          [
            1.60698,
            42.96932
          ],
          [
            1.60777,
            43.01897
          ],
          [
            1.60786,
            43.01919
          ],
          [
            1.64379,
            43.05078
          ],
          [
            1.6438,
            43.05104
          ],
          [
            1.6133,
            43.13383
          ],
          [
            1.61318,
            43.13434
          ],
          [
            1.61071,
            43.22353
          ],
          [
            1.61062,
            43.22385
          ],
          [
            1.56106,
            43.24328
          ],
          [
            1.56074,
            43.24356
          ],
          [
            1.52099,
            43.30476
          ],
          [
            1.52083,
            43.30495
          ],
          [
            1.43266,
            43.38462
          ],
          [
            1.43222,
            43.38518
          ],
          [
            1.42525,
            43.43645
          ],
          [
            1.42513,
            43.4368
          ],
          [
            1.38454,
            43.51844
          ],
          [
            1.3845,
            43.51864
          ],
          [
            1.45279,
            43.58184
          ],
          [
            1.45304,
            43.58216
          ],
          [
            1.45472,
            43.60939
          ]
        ]
      },
      "properties": {
        "start_station": "Latour-de-Carol \u2013 Enveitg",
        "end_station": "Toulouse",
        "start_time": "07:29",
        "end_time": "",
        "delay_mins": 0,
        "cost_euros": 12,
        "train_company": "SNCF",
        "train_number": "TER871470",
        "train_type": "Regional",
        "wifi": "No",
        "toilets": "Yes",
        "bike_space_rating": "N/A",
        "dep_country": "FR",
        "arr_country": "FR"
      }
    },
    {
      "type": "Feature",
      "geometry": {
        "type": "LineString",
        "coordinates": [
          [
            1.45472,
            43.60939
          ],
          [
            1.57127,
            43.47845
          ],
          [
            1.57398,
            43.47685
          ],
          [
            1.83696,
            43.3372
          ],
          [
            1.83781,
            43.33679
          ],
          [
            1.95487,
            43.31124
          ],
          [
            1.95509,
            43.31116
          ],
          [
            2.06091,
            43.25548
          ],
          [
            2.06259,
            43.25495
          ],
          [
            2.27324,
            43.2451
          ],
          [
            2.27415,
            43.24496
          ],
          [
            2.50411,
            43.18422
          ],
          [
            2.50502,
            43.18415
          ],
          [
            2.6993,
            43.17885
          ],
          [
            2.7005,
            43.1789
          ],
          [
            2.79904,
            43.20597
          ],
          [
            2.80101,
            43.20634
          ],
          [
            2.91767,
            43.21547
          ],
          [
            2.9181,
            43.21549
          ],
          [
            2.94531,
            43.18243
          ],
          [
            2.94604,
            43.18219
          ],
          [
            3.00566,
            43.19055
          ]
        ]
      },
      "properties": {
        "start_station": "Toulouse",
        "end_station": "Narbonne",
        "start_time": "",
        "end_time": "",
        "delay_mins": 0,
        "cost_euros": 30,
        "train_company": "SNCF",
        "train_number": "TER86975",
        "train_type": "Regional",
        "wifi": "No",
        "toilets": "Yes",
        "bike_space_rating": "N/A",
        "dep_country": "FR",
        "arr_country": "FR"
      }
    },
    {
      "type": "Feature",
      "geometry": {
        "type": "LineString",
        "coordinates": [
          [
            3.00566,
            43.19055
          ],
          [
            3.06563,
            43.2476
          ],
          [
            3.06602,
            43.24805
          ],
          [
            3.07654,
            43.27672
          ],
          [
            3.07673,
            43.27689
          ],
          [
            3.16413,
            43.33116
          ],
          [
            3.1647,
            43.33131
          ],
          [
            3.53272,
            43.31697
          ],
          [
            3.53367,
            43.31735
          ],
          [
            3.66729,
            43.41222
          ],
          [
            3.66783,
            43.4125
          ],
          [
            3.7494,
            43.42626
          ],
          [
            3.74987,
            43.42657
          ],
          [
            3.79131,
            43.49292
          ],
          [
            3.79178,
            43.4935
          ],
          [
            3.86627,
            43.56638
          ],
          [
            3.86665,
            43.56671
          ],
          [
            4.01338,
            43.63524
          ],
          [
            4.01417,
            43.63566
          ],
          [
            4.07544,
            43.68667
          ],
          [
            4.07634,
            43.68714
          ],
          [
            4.27502,
            43.72574
          ],
          [
            4.27641,
            43.72614
          ],
          [
            4.50782,
            43.81522
          ],
          [
            4.50797,
            43.81523
          ],
          [
            4.54619,
            43.7884
          ],
          [
            4.54681,
            43.78832
          ],
          [
            4.60708,
            43.80966
          ],
          [
            4.60792,
            43.80975
          ],
          [
            4.66039,
            43.79906
          ],
          [
            4.66064,
            43.79881
          ],
          [
            4.62663,
            43.71032
          ],
          [
            4.62661,
            43.71004
          ],
          [
            4.65246,
            43.6567
          ],
          [
            4.65271,
            43.65659
          ],
          [
            5.01613,
            43.57802
          ],
          [
            5.01784,
            43.57759
          ],
          [
            5.05731,
            43.53021
          ],
          [
            5.05753,
            43.53012
          ],
          [
            5.12539,
            43.53511
          ],
          [
            5.12571,
            43.53506
          ],
          [
            5.19048,
            43.49359
          ],
          [
            5.19119,
            43.49332
          ],
          [
            5.22623,
            43.50078
          ],
          [
            5.2266,
            43.50056
          ],
          [
            5.25356,
            43.4103
          ],
          [
            5.25377,
            43.40999
          ],
          [
            5.30494,
            43.36634
          ],
          [
            5.30519,
            43.36618
          ],
          [
            5.34512,
            43.35688
          ],
          [
            5.34529,
            43.35674
          ],
          [
            5.37406,
            43.29659
          ]
        ]
      },
      "properties": {
        "start_station": "Narbonne",
        "end_station": "Marseille",
        "start_time": "14:31",
        "end_time": "17:48",
        "delay_mins": 0,
        "cost_euros": 45.2,
        "train_company": "SNCF",
        "train_number": "TER876542",
        "train_type": "Regional",
        "wifi": "No",
        "toilets": "Yes",
        "bike_space_rating": "N/A",
        "dep_country": "FR",
        "arr_country": "FR"
      }
    },
    {
      "type": "Feature",
      "geometry": {
        "type": "LineString",
        "coordinates": [
          [
            5.37406,
            43.29659
          ],
          [
            5.36532,
            43.33196
          ],
          [
            5.3652,
            43.33196
          ],
          [
            5.3685,
            43.31222
          ],
          [
            5.36884,
            43.31197
          ],
          [
            5.42991,
            43.28939
          ],
          [
            5.43018,
            43.28934
          ],
          [
            5.57996,
            43.29755
          ],
          [
            5.58015,
            43.29751
          ],
          [
            5.55202,
            43.2655
          ],
          [
            5.55185,
            43.26521
          ],
          [
            5.55041,
            43.2392
          ],
          [
            5.55044,
            43.23889
          ],
          [
            5.59135,
            43.20052
          ],
          [
            5.5916,
            43.20041
          ],
          [
            5.62523,
            43.20966
          ],
          [
            5.62564,
            43.20962
          ],
          [
            5.6725,
            43.1835
          ],
          [
            5.67355,
            43.18314
          ],
          [
            5.70529,
            43.18505
          ],
          [
            5.70557,
            43.18495
          ],
          [
            5.72225,
            43.14548
          ],
          [
            5.72258,
            43.14523
          ],
          [
            5.7886,
            43.1283
          ],
          [
            5.78888,
            43.12823
          ],
          [
            5.87082,
            43.11551
          ],
          [
            5.87111,
            43.11552
          ],
          [
            5.91546,
            43.13325
          ],
          [
            5.91568,
            43.13324
          ],
          [
            6.00205,
            43.11533
          ],
          [
            6.00252,
            43.11543
          ],
          [
            6.05307,
            43.15621
          ],
          [
            6.05317,
            43.15636
          ],
          [
            6.04699,
            43.19544
          ],
          [
            6.04708,
            43.19567
          ],
          [
            6.09802,
            43.26396
          ],
          [
            6.09811,
            43.26403
          ],
          [
            6.15111,
            43.28995
          ],
          [
            6.15216,
            43.29028
          ],
          [
            6.27839,
            43.31336
          ],
          [
            6.27865,
            43.31349
          ],
          [
            6.29918,
            43.36333
          ],
          [
            6.29965,
            43.36377
          ],
          [
            6.35646,
            43.40035
          ],
          [
            6.3565,
            43.40037
          ],
          [
            6.42474,
            43.41292
          ],
          [
            6.42514,
            43.41315
          ],
          [
            6.43779,
            43.44651
          ],
          [
            6.43885,
            43.44703
          ],
          [
            6.57044,
            43.4707
          ],
          [
            6.57093,
            43.47069
          ],
          [
            6.67694,
            43.45672
          ],
          [
            6.67737,
            43.45661
          ],
          [
            6.78693,
            43.41266
          ],
          [
            6.78729,
            43.41259
          ],
          [
            6.8482,
            43.41833
          ],
          [
            6.84855,
            43.41843
          ],
          [
            6.86108,
            43.43569
          ],
          [
            6.86152,
            43.43578
          ],
          [
            6.88953,
            43.42977
          ],
          [
            6.88972,
            43.42982
          ],
          [
            6.91879,
            43.45102
          ],
          [
            6.91914,
            43.45148
          ],
          [
            6.94517,
            43.53222
          ],
          [
            6.94536,
            43.53237
          ],
          [
            7.11256,
            43.57149
          ],
          [
            7.11292,
            43.57167
          ],
          [
            7.14888,
            43.65831
          ],
          [
            7.14904,
            43.65846
          ],
          [
            7.21847,
            43.67151
          ],
          [
            7.21879,
            43.67164
          ],
          [
            7.26397,
            43.70556
          ]
        ]
      },
      "properties": {
        "start_station": "Marseille",
        "end_station": "Nice",
        "start_time": "18:57",
        "end_time": "21:38",
        "delay_mins": 0,
        "cost_euros": 39.8,
        "train_company": "SNCF",
        "train_number": "TER17493",
        "train_type": "Regional",
        "wifi": "No",
        "toilets": "Yes",
        "bike_space_rating": "N/A",
        "dep_country": "FR",
        "arr_country": "FR"
      }
    },
    {
      "type": "Feature",
      "geometry": {
        "type": "LineString",
        "coordinates": [
          [
            7.26397,
            43.70556
          ],
          [
            7.32602,
            43.70159
          ],
          [
            7.32642,
            43.70163
          ],
          [
            7.35776,
            43.72252
          ],
          [
            7.35839,
            43.72272
          ],
          [
            7.40199,
            43.72161
          ],
          [
            7.40217,
            43.72165
          ],
          [
            7.43191,
            43.75007
          ],
          [
            7.43373,
            43.75122
          ],
          [
            7.50297,
            43.77745
          ]
        ]
      },
      "properties": {
        "start_station": "Nice",
        "end_station": "Menton",
        "start_time": "22:19",
        "end_time": "21:11",
        "delay_mins": 0,
        "cost_euros": 9.2,
        "train_company": "SNCF",
        "train_number": "TER86097",
        "train_type": "Regional",
        "wifi": "No",
        "toilets": "Yes",
        "bike_space_rating": "N/A",
        "dep_country": "FR",
        "arr_country": "FR"
      }
    },
    {
      "type": "Feature",
      "geometry": {
        "type": "LineString",
        "coordinates": [
          [
            7.78566,
            43.82661
          ],
          [
            7.95253,
            43.85668
          ],
          [
            7.95351,
            43.85703
          ],
          [
            8.12568,
            43.94915
          ],
          [
            8.12707,
            43.95007
          ],
          [
            8.22427,
            44.05073
          ],
          [
            8.22455,
            44.05107
          ],
          [
            8.23153,
            44.09563
          ],
          [
            8.23166,
            44.09594
          ],
          [
            8.25969,
            44.13004
          ],
          [
            8.25991,
            44.13027
          ],
          [
            8.39983,
            44.21248
          ],
          [
            8.40261,
            44.21462
          ],
          [
            8.42482,
            44.27343
          ],
          [
            8.42516,
            44.2739
          ],
          [
            8.47011,
            44.30727
          ]
        ]
      },
      "properties": {
        "start_station": "Sanremo",
        "end_station": "Savona",
        "start_time": "12:46",
        "end_time": "14:25",
        "delay_mins": 0,
        "cost_euros": 34.5,
        "train_company": "Trenitalia",
        "train_number": "RE12267",
        "train_type": "Regional",
        "wifi": "No",
        "toilets": "Yes",
        "bike_space_rating": 3,
        "dep_country": "IT",
        "arr_country": "IT"
      }
    },
    {
      "type": "Feature",
      "geometry": {
        "type": "LineString",
        "coordinates": [
          [
            8.47011,
            44.30727
          ],
          [
            8.48123,
            44.32794
          ],
          [
            8.48227,
            44.32843
          ],
          [
            8.53427,
            44.33704
          ],
          [
            8.53479,
            44.33722
          ],
          [
            8.7442,
            44.42894
          ],
          [
            8.74525,
            44.42928
          ],
          [
            8.88464,
            44.41598
          ],
          [
            8.88473,
            44.41611
          ],
          [
            8.89596,
            44.49963
          ],
          [
            8.89601,
            44.4998
          ],
          [
            8.93254,
            44.54104
          ],
          [
            8.93278,
            44.54151
          ],
          [
            8.95105,
            44.61068
          ],
          [
            8.95108,
            44.61138
          ],
          [
            8.86524,
            44.70734
          ],
          [
            8.86503,
            44.70789
          ],
          [
            8.85266,
            44.89197
          ],
          [
            8.8528,
            44.89244
          ],
          [
            8.93421,
            44.96622
          ],
          [
            8.93491,
            44.96669
          ],
          [
            9.01996,
            45.00033
          ],
          [
            9.02032,
            45.00057
          ],
          [
            9.11424,
            45.08991
          ],
          [
            9.11444,
            45.0902
          ],
          [
            9.11243,
            45.13299
          ],
          [
            9.11308,
            45.13602
          ],
          [
            9.12235,
            45.16867
          ],
          [
            9.12335,
            45.17035
          ],
          [
            9.15144,
            45.195
          ],
          [
            9.15166,
            45.19546
          ],
          [
            9.1545,
            45.25719
          ],
          [
            9.15462,
            45.2575
          ],
          [
            9.24476,
            45.41217
          ],
          [
            9.24492,
            45.41256
          ],
          [
            9.23724,
            45.48507
          ]
        ]
      },
      "properties": {
        "start_station": "Savona",
        "end_station": "Milano Lambrate",
        "start_time": "14:35",
        "end_time": "17:27",
        "delay_mins": 0,
        "cost_euros": "",
        "train_company": "Trenitalia",
        "train_number": "RE3035",
        "train_type": "Regional",
        "wifi": "No",
        "toilets": "Yes",
        "bike_space_rating": 3,
        "dep_country": "IT",
        "arr_country": "IT"
      }
    },
    {
      "type": "Feature",
      "geometry": {
        "type": "LineString",
        "coordinates": [
          [
            9.23724,
            45.48507
          ],
          [
            9.24697,
            45.47143
          ],
          [
            9.24722,
            45.47145
          ],
          [
            9.53177,
            45.51148
          ],
          [
            9.53281,
            45.51149
          ],
          [
            9.67668,
            45.51001
          ],
          [
            9.67891,
            45.50979
          ],
          [
            9.76263,
            45.4873
          ],
          [
            9.76439,
            45.48736
          ],
          [
            10.0262,
            45.52375
          ],
          [
            10.02683,
            45.52385
          ],
          [
            10.08596,
            45.54641
          ],
          [
            10.08713,
            45.54654
          ],
          [
            10.21288,
            45.53218
          ]
        ]
      },
      "properties": {
        "start_station": "Milano Lambrate",
        "end_station": "Brescia",
        "start_time": "17:59",
        "end_time": "18:53",
        "delay_mins": 0,
        "cost_euros": "",
        "train_company": "Trenord",
        "train_number": "R4",
        "train_type": "Regional",
        "wifi": "No",
        "toilets": "Yes",
        "bike_space_rating": 3,
        "dep_country": "IT",
        "arr_country": "IT"
      }
    },
    {
      "type": "Feature",
      "geometry": {
        "type": "LineString",
        "coordinates": [
          [
            10.21288,
            45.53218
          ],
          [
            10.37929,
            45.47393
          ],
          [
            10.38001,
            45.47375
          ],
          [
            10.48213,
            45.45699
          ],
          [
            10.48269,
            45.45695
          ],
          [
            10.52154,
            45.46823
          ],
          [
            10.52288,
            45.46804
          ],
          [
            10.59979,
            45.43569
          ],
          [
            10.60024,
            45.43562
          ],
          [
            10.7123,
            45.44221
          ],
          [
            10.71276,
            45.44219
          ],
          [
            10.81539,
            45.42144
          ],
          [
            10.81676,
            45.42135
          ],
          [
            10.98274,
            45.42867
          ]
        ]
      },
      "properties": {
        "start_station": "Brescia",
        "end_station": "Verona Porta Nuova",
        "start_time": "",
        "end_time": "",
        "delay_mins": 0,
        "cost_euros": "",
        "train_company": "Trenitalia",
        "train_number": "R2637",
        "train_type": "Regional",
        "wifi": "No",
        "toilets": "Yes",
        "bike_space_rating": 3,
        "dep_country": "IT",
        "arr_country": "IT"
      }
    },
    {
      "type": "Feature",
      "geometry": {
        "type": "LineString",
        "coordinates": [
          [
            10.98274,
            45.42867
          ],
          [
            10.95258,
            45.43075
          ],
          [
            10.95244,
            45.43091
          ],
          [
            10.93919,
            45.48026
          ],
          [
            10.9388,
            45.4805
          ],
          [
            10.83195,
            45.50876
          ],
          [
            10.83155,
            45.50889
          ],
          [
            10.82071,
            45.52493
          ],
          [
            10.82078,
            45.52549
          ],
          [
            10.8503,
            45.60083
          ],
          [
            10.85048,
            45.60124
          ],
          [
            10.897,
            45.64822
          ],
          [
            10.89728,
            45.64862
          ],
          [
            10.90665,
            45.68244
          ],
          [
            10.90684,
            45.68269
          ],
          [
            10.94479,
            45.72853
          ],
          [
            10.94511,
            45.72881
          ],
          [
            11.01135,
            45.77167
          ],
          [
            11.0115,
            45.77191
          ],
          [
            11.02162,
            45.79525
          ],
          [
            11.02162,
            45.79558
          ],
          [
            11.00329,
            45.86292
          ],
          [
            11.00345,
            45.86317
          ],
          [
            11.03074,
            45.88018
          ],
          [
            11.03096,
            45.88042
          ],
          [
            11.04251,
            45.91506
          ],
          [
            11.04305,
            45.91557
          ],
          [
            11.08277,
            45.9273
          ],
          [
            11.08305,
            45.92745
          ],
          [
            11.10862,
            45.95408
          ],
          [
            11.10897,
            45.95471
          ],
          [
            11.12806,
            46.04102
          ],
          [
            11.12801,
            46.04189
          ],
          [
            11.12176,
            46.07836
          ],
          [
            11.1217,
            46.07849
          ],
          [
            11.08343,
            46.13379
          ],
          [
            11.08369,
            46.13442
          ],
          [
            11.13764,
            46.22013
          ],
          [
            11.13801,
            46.22053
          ],
          [
            11.20975,
            46.2489
          ],
          [
            11.21071,
            46.24967
          ],
          [
            11.29493,
            46.3573
          ],
          [
            11.29509,
            46.35749
          ],
          [
            11.34174,
            46.48433
          ],
          [
            11.3421,
            46.48471
          ],
          [
            11.36622,
            46.49947
          ],
          [
            11.36633,
            46.49948
          ],
          [
            11.42737,
            46.48568
          ],
          [
            11.42905,
            46.48585
          ],
          [
            11.48001,
            46.50849
          ],
          [
            11.48098,
            46.50904
          ],
          [
            11.52205,
            46.55536
          ],
          [
            11.52476,
            46.55935
          ],
          [
            11.53263,
            46.60123
          ]
        ]
      },
      "properties": {
        "start_station": "Verona Porta Nuova",
        "end_station": "Ponte Gardena/Waidbruck",
        "start_time": "",
        "end_time": "",
        "delay_mins": 0,
        "cost_euros": "",
        "train_company": "Trenitalia",
        "train_number": "",
        "train_type": "Regional",
        "wifi": "No",
        "toilets": "Yes",
        "bike_space_rating": 3,
        "dep_country": "IT",
        "arr_country": "IT"
      }
    },
    {
      "type": "Feature",
      "geometry": {
        "type": "LineString",
        "coordinates": [
          [
            11.53263,
            46.60123
          ],
          [
            11.55663,
            46.63424
          ],
          [
            11.55691,
            46.63446
          ],
          [
            11.61857,
            46.66712
          ],
          [
            11.61879,
            46.66733
          ],
          [
            11.64998,
            46.71437
          ],
          [
            11.64998,
            46.71476
          ],
          [
            11.63706,
            46.77245
          ],
          [
            11.63691,
            46.77261
          ],
          [
            11.54002,
            46.81412
          ],
          [
            11.53967,
            46.81434
          ],
          [
            11.50688,
            46.86045
          ],
          [
            11.50657,
            46.8607
          ],
          [
            11.43176,
            46.90132
          ],
          [
            11.43156,
            46.90157
          ],
          [
            11.44949,
            46.93175
          ],
          [
            11.44937,
            46.93189
          ],
          [
            11.39353,
            46.95169
          ],
          [
            11.39341,
            46.95191
          ],
          [
            11.47842,
            46.97528
          ],
          [
            11.47873,
            46.97541
          ],
          [
            11.50537,
            47.00236
          ]
        ]
      },
      "properties": {
        "start_station": "Ponte Gardena/Waidbruck",
        "end_station": "Brennero/Brenner",
        "start_time": "",
        "end_time": "",
        "delay_mins": 0,
        "cost_euros": "",
        "train_company": "Trenitalia",
        "train_number": "",
        "train_type": "Regional",
        "wifi": "No",
        "toilets": "Yes",
        "bike_space_rating": 3,
        "dep_country": "IT",
        "arr_country": "IT"
      }
    }
  ]
}